example_package_nagore_ainhoa2/__init__.py
example_package_nagore_ainhoa2/functions.py
example_package_nagore_ainhoa2-0.0.1.dist-info/METADATA
example_package_nagore_ainhoa2-0.0.1.dist-info/WHEEL
example_package_nagore_ainhoa2-0.0.1.dist-info/licenses/LICENSE
example_package_nagore_ainhoa2-0.0.1.dist-info/RECORD
